cqc/MessageHandler.py
cqc/Protocol.py
cqc/__init__.py
cqc/cqcHeader.py
cqc/entInfoHeader.py
cqc/hostConfig.py
cqc/util.py
cqc/pythonLib/__init__.py
cqc/pythonLib/cqc_connection.py
cqc/pythonLib/cqc_handler.py
cqc/pythonLib/cqc_mix.py
cqc/pythonLib/cqc_to_file.py
cqc/pythonLib/qubit.py
cqc/pythonLib/util.py
cqc/pythonLib_protocols/__init__.py
cqc/pythonLib_protocols/coinflip_leader.py
cqc/pythonLib_protocols/measurements.py
cqc/pythonLib_protocols/wstate.py
cqc-3.2.3.dist-info/LICENSE
cqc-3.2.3.dist-info/METADATA
cqc-3.2.3.dist-info/WHEEL
cqc-3.2.3.dist-info/top_level.txt
cqc-3.2.3.dist-info/RECORD
