Metadata-Version: 2.1
Name: cqc
Version: 3.2.3
Summary: The CQC interface
Home-page: https://github.com/SoftwareQuTech/CQC-Python
Author: Axel Dahlberg
Author-email: e.a.dahlberg@tudelft.nl
License: UNKNOWN
Platform: UNKNOWN
Classifier: Programming Language :: Python :: 3
Classifier: License :: OSI Approved :: MIT License
Classifier: Operating System :: OS Independent
